{"trial_id": "0017", "hyperparameters": {"space": [{"class_name": "Choice", "config": {"name": "shared_units", "default": 32, "conditions": [], "values": [32, 64, 128], "ordered": true}}, {"class_name": "Float", "config": {"name": "shared_dropout", "default": 0.1, "conditions": [], "min_value": 0.1, "max_value": 0.5, "step": 0.1, "sampling": "linear"}}, {"class_name": "Int", "config": {"name": "high_dense", "default": null, "conditions": [], "min_value": 4, "max_value": 16, "step": 4, "sampling": "linear"}}, {"class_name": "Int", "config": {"name": "low_dense", "default": null, "conditions": [], "min_value": 4, "max_value": 16, "step": 4, "sampling": "linear"}}, {"class_name": "Int", "config": {"name": "body_dense", "default": null, "conditions": [], "min_value": 4, "max_value": 16, "step": 4, "sampling": "linear"}}, {"class_name": "Float", "config": {"name": "lr", "default": 0.0001, "conditions": [], "min_value": 0.0001, "max_value": 0.01, "step": null, "sampling": "log"}}], "values": {"shared_units": 64, "shared_dropout": 0.1, "high_dense": 16, "low_dense": 16, "body_dense": 16, "lr": 0.0004605666456567159, "tuner/epochs": 2, "tuner/initial_epoch": 0, "tuner/bracket": 3, "tuner/round": 0}}, "metrics": {"metrics": {"loss": {"direction": "min", "observations": [{"value": [0.7355796098709106], "step": 0}]}, "high_output_loss": {"direction": "min", "observations": [{"value": [0.11810379475355148], "step": 0}]}, "low_output_loss": {"direction": "min", "observations": [{"value": [0.07121037691831589], "step": 0}]}, "body_output_loss": {"direction": "min", "observations": [{"value": [1.070466160774231], "step": 0}]}, "val_loss": {"direction": "min", "observations": [{"value": [0.4465721547603607], "step": 0}]}, "val_high_output_loss": {"direction": "min", "observations": [{"value": [0.0837816372513771], "step": 0}]}, "val_low_output_loss": {"direction": "min", "observations": [{"value": [0.051167767494916916], "step": 0}]}, "val_body_output_loss": {"direction": "min", "observations": [{"value": [0.601321280002594], "step": 0}]}}}, "score": 0.4465721547603607, "best_step": 0, "status": "COMPLETED", "message": null}